assets/img/diagrams-otc.png
diagrams/__init__.py
diagrams/alibabacloud/__init__.py
diagrams/alibabacloud/analytics.py
diagrams/alibabacloud/application.py
diagrams/alibabacloud/communication.py
diagrams/alibabacloud/compute.py
diagrams/alibabacloud/database.py
diagrams/alibabacloud/iot.py
diagrams/alibabacloud/network.py
diagrams/alibabacloud/security.py
diagrams/alibabacloud/storage.py
diagrams/alibabacloud/web.py
diagrams/aws/__init__.py
diagrams/aws/analytics.py
diagrams/aws/ar.py
diagrams/aws/blockchain.py
diagrams/aws/business.py
diagrams/aws/compute.py
diagrams/aws/cost.py
diagrams/aws/database.py
diagrams/aws/devtools.py
diagrams/aws/enablement.py
diagrams/aws/enduser.py
diagrams/aws/engagement.py
diagrams/aws/game.py
diagrams/aws/general.py
diagrams/aws/integration.py
diagrams/aws/iot.py
diagrams/aws/management.py
diagrams/aws/media.py
diagrams/aws/migration.py
diagrams/aws/ml.py
diagrams/aws/mobile.py
diagrams/aws/network.py
diagrams/aws/quantum.py
diagrams/aws/robotics.py
diagrams/aws/satellite.py
diagrams/aws/security.py
diagrams/aws/storage.py
diagrams/azure/__init__.py
diagrams/azure/analytics.py
diagrams/azure/compute.py
diagrams/azure/database.py
diagrams/azure/devops.py
diagrams/azure/general.py
diagrams/azure/identity.py
diagrams/azure/integration.py
diagrams/azure/iot.py
diagrams/azure/migration.py
diagrams/azure/ml.py
diagrams/azure/mobile.py
diagrams/azure/network.py
diagrams/azure/security.py
diagrams/azure/storage.py
diagrams/azure/web.py
diagrams/base/__init__.py
diagrams/c4/__init__.py
diagrams/custom/__init__.py
diagrams/digitalocean/__init__.py
diagrams/digitalocean/compute.py
diagrams/digitalocean/database.py
diagrams/digitalocean/network.py
diagrams/digitalocean/storage.py
diagrams/elastic/__init__.py
diagrams/elastic/agent.py
diagrams/elastic/beats.py
diagrams/elastic/elasticsearch.py
diagrams/elastic/enterprisesearch.py
diagrams/elastic/observability.py
diagrams/elastic/orchestration.py
diagrams/elastic/saas.py
diagrams_otc-0.23.6.dist-info/LICENSE
diagrams_otc-0.23.6.dist-info/METADATA
diagrams_otc-0.23.6.dist-info/WHEEL
diagrams_otc-0.23.6.dist-info/RECORD
